MANIFEST.in
README.rst
generate-runner.py
setup.py
generate_pip.egg-info/PKG-INFO
generate_pip.egg-info/SOURCES.txt
generate_pip.egg-info/dependency_links.txt
generate_pip.egg-info/entry_points.txt
generate_pip.egg-info/top_level.txt
src/__init__.py
src/__main__.py
src/generate_pip.py
src/constructor/__init__.py
src/constructor/osx.py
src/constructor/system.py
src/constructor/windows.py